{
    "http://mewa-styl.ru/ishop/product/939": [
        "939",
        "Купальник PAOLA , разм.40-44 (46-50)",
        "Купальник Paola , Push-up  , с чашкой , на косточках . плечевые бретельки регулируются. Схади надежная металлическая застежка . ",
        "2500",
        "http://mewa-styl.ru/imgtmp/orign/data/1/FN7A3322.jpg",
        "44D, 46B, 46C, 46D, 46E, 48B, 48C, 48D, 50B, 50C, 52B"
    ],
    "http://mewa-styl.ru/ishop/product/940": [
        "940",
        "Купальник PAOLA  , разм.40-44 (46-50)",
        "Купальник Paola , Push-up  , с чашкой , на косточках . плечевые бретельки регулируются. Схади надежная металлическая застежка . ",
        "2500",
        "http://mewa-styl.ru/imgtmp/orign/data/1/FN7A4319.jpg",
        "44B, 44C, 44D, 46B, 46C, 46D, 46E, 48B, 48C, 48D, 50B, 50C, 52B"
    ],
    "http://mewa-styl.ru/ishop/product/786": [
        "786",
        "001.Купальник  MEGAN-G,C/K,  разм.40-50 (46-56 ) ",
        "Купальник Megan , раз. 40-50 (46-56) .  Мягкая чашка , на косточках . плечевые бретельки регулируются . Сзади надежная металлическая застёжка . Роскошная модель на большую грудь . ",
        "2700",
        "http://mewa-styl.ru/imgtmp/orign/data/1/FN7A4969-cmyk.jpg",
        "46C, 46D, 46F, 48E, 50D, 50E, 50F, 52C, 52D, 52E, 52F, 54C, 54D, 54E, 56C, 56D, 56E"
    ],
    "http://mewa-styl.ru/ishop/product/828": [
        "828",
        "005.Купальник  MEGAN-GZ, C/403,  разм.40-50 (46-56 ) ",
        "Купальник Megan , раз. 40-50 (46-56) .  Мягкая чашка , на косточках . плечевые бретельки регулируются . Сзади надежная металлическая застёжка . Роскошная модель на большую грудь . ",
        "2500",
        "http://mewa-styl.ru/imgtmp/orign/data/1/FN7A5353-r.jpg",
        "46C, 46D, 46F, 48C, 48D, 48E, 50C, 50D, 50E, 52C, 52D, 52E, 52F, 54C, 54D, 54E, 56C, 56D, 56E"
    ],
    "http://mewa-styl.ru/ishop/product/881": [
        "881",
        "Купальник  MEGAN,  разм.40-50 (46-56 ) ",
        "Купальник Megan , раз. 40-50 (46-56) .  Мягкая чашка , на косточках . плечевые бретельки регулируются . Сзадиe надежная металлическая застёжка . Роскошная модель на большую грудь . ",
        "2500",
        "http://mewa-styl.ru/imgtmp/orign/data/1/FN7A5390.jpg",
        "46C, 46D, 46F, 48C, 48D, 48E, 48F, 50D, 50E, 52D, 52E, 54C, 54D, 54E, 56C, 56D, 56E"
    ],
    "http://mewa-styl.ru/ishop/product/891": [
        "891",
        "002.Купальник  MEGAN-G,C/C,  разм.40-50 (46-56 ) ",
        "Купальник Megan , раз. 40-50 (46-56) .  Мягкая чашка , на косточках . плечевые бретельки регулируются . Сзадиe надежная металлическая застёжка . Роскошная модель на большую грудь . ",
        "2500",
        "http://mewa-styl.ru/imgtmp/orign/data/1/FN7A5330.jpg",
        "46C, 46D, 46F, 48D, 48E, 50C, 50D, 50E, 50F, 52C, 52D, 52E, 52F, 54C, 54D, 54E, 56C, 56D, 56E"
    ],
    "http://mewa-styl.ru/ishop/product/897": [
        "897",
        "004.Купальник  MEGAN-GZ,C/406,  разм.40-50 (46-56 ) ",
        "Купальник Megan , раз. 40-50 (46-56) .  Мягкая чашка , на косточках . плечевые бретельки регулируются . Сзадиe надежная металлическая застёжка . Роскошная модель на большую грудь . ",
        "2500",
        "http://mewa-styl.ru/imgtmp/orign/data/1/FN7A5340.jpg",
        "46C, 46D, 46E, 46F, 48D, 50D, 50E, 50F, 52C, 52D, 52E, 52F, 54C, 54D, 54E, 56C, 56D, 56E"
    ],
    "http://mewa-styl.ru/ishop/product/922": [
        "922",
        "003.Купальник  MEGAN-G,C/J1,  разм.40-50 (46-56 ) ",
        "Купальник Megan , раз. 40-50 (46-56) .  Мягкая чашка , на косточках . плечевые бретельки регулируются . Сзадиe надежная металлическая застёжка . Роскошная модель на большую грудь . ",
        "2700",
        "http://mewa-styl.ru/imgtmp/orign/data/1/FN7A5307.jpg",
        "46C, 46D, 48E, 50C, 50D, 50E, 52C, 52D, 52E, 52F, 54C, 54D, 54E, 56C, 56D, 56E"
    ],
    "http://mewa-styl.ru/ishop/product/941": [
        "",
        "",
        "",
        "",
        "",
        ""
    ],
    "http://mewa-styl.ru/ishop/product/901": [
        "901",
        "Купальник SARA ",
        "Купальник Sara лиф в виде треугольных чашек , завязки на шее и объеме . Чашка без косточки с push-ap , благодаря эффекту обжимания, он мягко формирует и подчеркивает бюст.",
        "2500",
        "http://mewa-styl.ru/imgtmp/orign/data/1/FN7A4353.jpg",
        "42B, 42C, 42E, 44C, 44D, 44E, 46B"
    ],
    "http://mewa-styl.ru/ishop/product/935": [
        "935",
        "Купальник Sara",
        "Купальник Sara лиф в виде треугольных чашек , завязки на шее и объеме . Чашка без косточки с push-ap , благодаря эффекту обжимания, он мягко формирует и подчеркивает бюст.",
        "2500",
        "http://mewa-styl.ru/imgtmp/orign/data/1/IMG-20220520-WA0001.jpg",
        "42B, 42C, 42D, 42E, 44D, 46B, 46C, 46D, 48B, 48C"
    ],
    "http://mewa-styl.ru/ishop/product/936": [
        "936",
        "Купальник Sara",
        "Купальник Sara лиф в виде треугольных чашек , завязки на шее и объеме . Чашка без косточки с push-ap , благодаря эффекту обжимания, он мягко формирует и подчеркивает бюст.",
        "2000",
        "http://mewa-styl.ru/imgtmp/orign/data/2/data3011gab00003.jpg",
        "42E"
    ],
    "http://mewa-styl.ru/ishop/product/938": [
        "938",
        "Купальник Sara",
        "Купальник Sara лиф в виде треугольных чашек , завязки на шее и объеме . Чашка без косточки с push-ap , благодаря эффекту обжимания, он мягко формирует и подчеркивает бюст.",
        "2500",
        "http://mewa-styl.ru/imgtmp/orign/data/1/Gabbiano2022/gabAAA111.jpg",
        "42B, 42C, 42D, 42E, 44B, 44C, 44D, 44E, 46B, 46C, 48B"
    ],
    "http://mewa-styl.ru/ishop/product/896": [
        "896",
        " Купальник Evita GT-01 , разм.36-44 (42-50)",
        "Купальник Evita-GT, разм.36 - 44 . Push - up .  Чашка бандо на косточке .сьемные плечевые бретельки, металлическая застежка с возможностью регулировки обьема",
        "2100",
        "http://mewa-styl.ru/imgtmp/orign/data/2919/gab314.jpg",
        "42E"
    ],
    "http://mewa-styl.ru/ishop/product/921": [
        "921",
        "Купальник Evita GT-01 , разм.36-44 (42-50)",
        "Купальник Evita-GT, разм.36 - 44 . Push - up .  Чашка бандо на косточке .сьемные плечевые бретельки, металлическая застежка с возможностью регулировки обьема",
        "2100",
        "http://mewa-styl.ru/imgtmp/orign/data/2919/gab003.jpg",
        "44E"
    ],
    "http://mewa-styl.ru/ishop/product/923": [
        "923",
        " Купальник Evita GT-01 , разм.36-44 (42-50)",
        "Купальник Evita-GT, разм.36 - 44 . Push - up .  Чашка бандо на косточке .сьемные плечевые бретельки, металлическая застежка с возможностью регулировки обьема",
        "2100",
        "http://mewa-styl.ru/imgtmp/orign/data/2919/gab01.jpg",
        "42C, 42E, 44E"
    ],
    "http://mewa-styl.ru/ishop/product/924": [
        "924",
        " Купальник Evita G-01 , разм.36-44 (42-50)",
        "Купальник Evita разм.36 - 44 . Push - up .  Чашка бандо на косточке . Сьемные плечевые бретельки , металлическая застежка с возможностью регулировки обьема",
        "2700",
        "http://mewa-styl.ru/imgtmp/orign/data/1/Gabbiano2022/FN7A2761-r.jpg",
        "42B, 44B, 44C, 46B, 46C, 48B, 48C, 48D, 50B, 50C"
    ],
    "http://mewa-styl.ru/ishop/product/929": [
        "929",
        " Купальник Evita разм.36-44 (42-50)  ",
        "Купальник Evita разм.36-44 (42-50)  . С чашкой , на косточках , съемные вставки Push-up . Бретельки регулируются и отсоединяются . Надежная металлическая застежка с возможностью регулировки объема . ",
        "2700",
        "http://mewa-styl.ru/imgtmp/orign/data/1/FN7A5824-r.jpg",
        "46D, 48D, 50B"
    ],
    "http://mewa-styl.ru/ishop/product/892": [
        "892",
        " Купальник LIZZY-GT,  разм.36-44 (42-50)",
        "Купальник LIZZY-GT, разм.36-44 . Push - up .  С чашкой , без косточек . На шее и на спине завязки .",
        "1600",
        "http://mewa-styl.ru/imgtmp/orign/data/1/data2datagab7901.jpg",
        "44B, 44C, 44E, 46B, 46C, 46D, 46E, 48B, 48C, 48D"
    ],
    "http://mewa-styl.ru/ishop/product/893": [
        "893",
        "А1.Купальник LIZZY-GT,  разм.36-44 (42-50)",
        "Купальник LIZZY-GT, разм.36-44 . Push - up .  С чашкой , без косточек . На шее и на спине завязки .",
        "1600",
        "http://mewa-styl.ru/imgtmp/orign/data/gab775.jpg",
        "44B, 44C, 44D, 44E, 46B, 46C, 46E"
    ],
    "http://mewa-styl.ru/ishop/product/906": [
        "906",
        "А2.Купальник LIZZY-GT, разм.36-44 (42-50) ",
        "Купальник LIZZY-GT, разм.36-44 . Push - up .  С чашкой , без косточек . На шее и на спине завязки .",
        "1600",
        "http://mewa-styl.ru/imgtmp/orign/data/1/datagab7731.jpg",
        "44B, 44C, 44D, 46B, 46C"
    ],
    "http://mewa-styl.ru/ishop/product/907": [
        "907",
        "А3.Купальник LIZZY-GT, разм.36-44 (42-50) ",
        "Купальник LIZZY-GT, разм.36-44 . Push - up .  С чашкой , без косточек . На шее и на спине завязки .",
        "1600",
        "http://mewa-styl.ru/imgtmp/orign/data/2919/gab301.jpg",
        "42B, 42D, 44B, 44D, 46B, 46C, 46D"
    ],
    "http://mewa-styl.ru/ishop/product/908": [
        "908",
        "Купальник LIZZY-GT, разм.36-44 (42-50) ",
        "Купальник LIZZY-GT, разм.36-44 . Push - up .  С чашкой , без косточек . На шее и на спине завязки .",
        "1600",
        "http://mewa-styl.ru/imgtmp/orign/data/1/data2919gab302A.jpg",
        "42B, 42C, 42D, 44B, 44C, 44D, 44E, 46C, 46D"
    ],
    "http://mewa-styl.ru/ishop/product/915": [
        "915",
        "Купальник LILLY-GT, разм.36-44 (42-50) ",
        "Купальник LILLY-GT, разм.36-44 . Push - up .  С чашкой , без косточек . На шее и на спине завязки .",
        "1900",
        "http://mewa-styl.ru/imgtmp/orign/data/2919/gab320.jpg",
        "46E, 48C"
    ],
    "http://mewa-styl.ru/ishop/product/894": [
        "894",
        " Купальник LILLY-GT,  разм.36-44 (42-50)",
        "Купальник LILLY-GT, разм.36-44 . Push - up .  С чашкой , без косточек . На шее и на спине завязки .",
        "1900",
        "http://mewa-styl.ru/imgtmp/orign/data/2/datagab792.jpg",
        "42D, 44B, 44C, 44D, 44E, 46B"
    ],
    "http://mewa-styl.ru/ishop/product/895": [
        "895",
        " Купальник LILLY-GT,  разм.36-44 (42-50)",
        "Купальник LILLY-GT, разм.36-44 . Push - up .  С чашкой , без косточек . На шее и на спине завязки .",
        "1900",
        "http://mewa-styl.ru/imgtmp/orign/data/2/datagab793.jpg",
        "42D, 44D, 44E, 46C"
    ],
    "http://mewa-styl.ru/ishop/product/909": [
        "909",
        "Купальник LILLY-GT, разм.36-44 (42-50) ",
        "Купальник LILLY-GT, разм.36-44 . Push - up .  С чашкой , без косточек . На шее и на спине завязки .",
        "1900",
        "http://mewa-styl.ru/imgtmp/orign/data/1/Gabbiano2022/LILLY-GT01J.jpg",
        "42C, 44B, 44C, 44E, 46B, 46C"
    ],
    "http://mewa-styl.ru/ishop/product/925": [
        "925",
        "Купальник Sally",
        "Купальник Sally .  Мягкая чашка , вкладки съемные , без косточек . На шее и на спине завязки . ",
        "2100",
        "http://mewa-styl.ru/imgtmp/orign/data/start/CFC3E6C8-1780-4351-888D-6DA550F44BD0.jpeg",
        "42, 44B, 44C, 46"
    ],
    "http://mewa-styl.ru/ishop/product/833": [
        "833",
        "1.Купальник Glovanna разм.36-44 (42-50) ",
        "Купальник Glovanna разм.36-44 (42-50) . С чашкой , без косточек .  Push-up . На шее и на спине завязки .",
        "2100",
        "http://mewa-styl.ru/imgtmp/orign/data/2919/gab719.jpg",
        "44E"
    ],
    "http://mewa-styl.ru/ishop/product/917": [
        "917",
        "1.04. Купальник Marissa разм.36-44 (42-50) ",
        "Купальник Marissa разм.36-44 (42-50) . С чашкой , на косточках , съемные вставки Push-up . Бретельки регулируются и отсоединяются . Надежная металлическая застежка с возможностью регулировки объема . ",
        "2100",
        "http://mewa-styl.ru/imgtmp/orign/data/2919/gab324.jpg",
        "42B, 42D, 44C"
    ],
    "http://mewa-styl.ru/ishop/product/918": [
        "918",
        "Купальник Glovanna разм.36-44 (42-50) ",
        "Купальник Glovanna разм.36-44 (42-50) . С чашкой , без косточек .  Push-up . На шее и на спине завязки .",
        "2100",
        "http://mewa-styl.ru/imgtmp/orign/data/2919/gab325.jpg",
        "44D, 44E, 44F, 46B, 46E"
    ],
    "http://mewa-styl.ru/ishop/product/810": [
        "810",
        "1.2. Купальник Marissa разм.36-44 (42-50)",
        "Купальник Marissa разм.36-44 (42-50) . С чашкой , на косточках , съемные вставки Push-up . Бретельки регулируются и отсоединяются . Надежная металлическая застежка с возможностью регулировки объема . ",
        "2100",
        "http://mewa-styl.ru/imgtmp/orign/data/2919/gab755.jpg",
        "42D, 42E, 44D, 44E, 44F"
    ],
    "http://mewa-styl.ru/ishop/product/814": [
        "814",
        "1.3.Купальник Aya разм.36-44 (42-50) ",
        "Купальник Aya разм.36-44 (42-50) . Push - up .  С чашкой , без косточек . На шее и на спине завязки . ",
        "1600",
        "http://mewa-styl.ru/imgtmp/orign/data/2919/gab735.jpg",
        "42F, 44E, 44F, 46E"
    ],
    "http://mewa-styl.ru/ishop/product/825": [
        "825",
        "1.10.Купальник Rita разм.36-44 (42-50 ) ",
        "Купальник Rita разм.36-44 (42-50 ). С чашкой , на косточках , съемные вставки Push-up . Бретельки регулируются. Сзади надежная металлическая застежка с возможностью регулировки объема .",
        "2000",
        "http://mewa-styl.ru/imgtmp/orign/data/2919/gab711.jpg",
        "42C, 44E, 46B, 46C, 46D"
    ],
    "http://mewa-styl.ru/ishop/product/831": [
        "831",
        "1.11. Купальник Rita разм.36-44 (42-50 ) ",
        "Купальник Rita разм.36-44 (42-50 ). С чашкой , на косточках , съемные вставки Push-up . Бретельки регулируются. Сзади надежная металлическая застежка с возможностью регулировки объема .",
        "1300",
        "http://mewa-styl.ru/imgtmp/orign/data/2919/gab715.jpg",
        "44D"
    ],
    "http://mewa-styl.ru/ishop/product/855": [
        "855",
        "1.12.  Купальник Rita разм.36-44 (42-50 )",
        "Купальник Rita разм.36-44 (42-50 ). С чашкой , на косточках , съемные вставки Push-up . Бретельки регулируются. Сзади надежная металлическая застежка с возможностью регулировки объема .",
        "2000",
        "http://mewa-styl.ru/imgtmp/orign/data/2919/gab747.jpg",
        "42C, 44B, 44C, 44D, 46C, 46D"
    ],
    "http://mewa-styl.ru/ishop/product/132": [
        "132",
        "1а. Купальник Rita разм.36-44 (42-50 ) ",
        "Купальник Rita разм.36-44 (42-50 ). С чашкой , на косточках , съемные вставки Push-up . Бретельки регулируются. Сзади надежная металлическая застежка с возможностью регулировки объема .",
        "1600",
        "http://mewa-styl.ru/imgtmp/orign/data/2018/gab636.jpg",
        "42B, 44C, 44D"
    ],
    "http://mewa-styl.ru/ishop/product/430": [
        "430",
        "1б. Купальник Rita разм.36-44 (42-50 )",
        "Купальник Rita разм.36-44 (42-50 ). С чашкой , на косточках , съемные вставки Push-up . Бретельки регулируются. Сзади надежная металлическая застежка с возможностью регулировки объема .",
        "1600",
        "http://mewa-styl.ru/imgtmp/orign/data/2919/gab774.jpg",
        "42B, 44B, 44D, 46B, 46C, 46D, 48B"
    ],
    "http://mewa-styl.ru/ishop/product/789": [
        "789",
        "1г.Купальник Rita разм.36-44 (42-50 ) ",
        "Купальник Rita разм.36-44 (42-50 ). С чашкой , на косточках , съемные вставки Push-up . Бретельки регулируются. Сзади надежная металлическая застежка с возможностью регулировки объема .",
        "2000",
        "http://mewa-styl.ru/imgtmp/orign/data/2919/gab763.jpg",
        "44C, 44D, 46B, 46D"
    ],
    "http://mewa-styl.ru/ishop/product/827": [
        "827",
        "1л.Купальник Marissa разм.36-44 (42-50) ",
        "Купальник Marissa разм.36-44 (42-50) . С чашкой , на косточках , съемные вставки Push-up . Бретельки регулируются и отсоединяются . Надежная металлическая застежка с возможностью регулировки объема .   ",
        "2100",
        "http://mewa-styl.ru/imgtmp/orign/data/2919/gab-2.jpg",
        "44D, 44E"
    ],
    "http://mewa-styl.ru/ishop/product/913": [
        "913",
        "2. Купальник Marissa разм.36-44 (42-50) ",
        "Купальник Marissa разм.36-44 (42-50) . С чашкой , на косточках , съемные вставки Push-up . Бретельки регулируются и отсоединяются . Надежная металлическая застежка с возможностью регулировки объема .   ",
        "1300",
        "http://mewa-styl.ru/imgtmp/orign/data/2919/gab319.jpg",
        "42B, 44C, 44D, 46B"
    ],
    "http://mewa-styl.ru/ishop/product/652": [
        "652",
        "2а . Купальник Marissa разм.36-44 (42-50) ",
        "Купальник Marissa разм.36-44 (42-50) . С чашкой , на косточках , съемные вставки Push-up . Бретельки регулируются и отсоединяются . Надежная металлическая застежка с возможностью регулировки объема .   ",
        "1300",
        "http://mewa-styl.ru/imgtmp/orign/data/Gabbiano/gab359.jpg",
        "42B, 44C, 44D"
    ],
    "http://mewa-styl.ru/ishop/product/653": [
        "653",
        "2б . Купальник Marissa разм.36-44 (42-50)  ",
        "Купальник Marissa разм.36-44 (42-50) . С чашкой , на косточках , съемные вставки Push-up . Бретельки регулируются и отсоединяются . Надежная металлическая застежка с возможностью регулировки объема .   ",
        "1600",
        "http://mewa-styl.ru/imgtmp/orign/data/Gabbiano/gab361.jpg",
        "42B, 44B, 44C, 44D"
    ],
    "http://mewa-styl.ru/ishop/product/684": [
        "684",
        "2в . Купальник Marissa разм.36-44 (42-50) ",
        "Купальник Marissa разм.36-44 (42-50) . С чашкой , на косточках , съемные вставки Push-up . Бретельки регулируются и отсоединяются . Надежная металлическая застежка с возможностью регулировки объема .   ",
        "1300",
        "http://mewa-styl.ru/imgtmp/orign/data/2/gab429.jpg",
        "42C, 44C, 44D"
    ],
    "http://mewa-styl.ru/ishop/product/685": [
        "685",
        "2г. Купальник Marissa разм.36-44 (42-50) ",
        "Купальник Marissa разм.36-44 (42-50) . С чашкой , на косточках , съемные вставки Push-up . Бретельки регулируются и отсоединяются . Надежная металлическая застежка с возможностью регулировки объема .   ",
        "1300",
        "http://mewa-styl.ru/imgtmp/orign/data/2/gab431.jpg",
        "42B, 44C, 44D"
    ],
    "http://mewa-styl.ru/ishop/product/910": [
        "910",
        "2д.Купальник Marissa разм.36-44 (42-50) ",
        "Купальник Marissa разм.36-44 . Push - up .  С чашкой , без косточек . На шее и на спине завязки .",
        "1300",
        "http://mewa-styl.ru/imgtmp/orign/data/1/Gabbiano2022/s008MARISA1_v01FFF.jpg",
        "42B, 44B, 44C, 44D"
    ],
    "http://mewa-styl.ru/ishop/product/488": [
        "488",
        "4а.Купальник Elin разм.36",
        "Купальник Elin разм.36 . С чашкой , на косточках , съемные вставки Push-up . Бретельки регулируются и отсоединяются . Надежная металлическая застежка с возможностью регулировки объема .  ",
        "1300",
        "http://mewa-styl.ru/imgtmp/orign/data/1/gab82.jpg",
        "42"
    ],
    "http://mewa-styl.ru/ishop/product/499": [
        "499",
        "6а.Купальник Elin разм.36",
        "Купальник Elin разм.36 . С чашкой , на косточках , съемные вставки Push-up . Бретельки регулируются и отсоединяются . Надежная металлическая застежка с возможностью регулировки объема .  ",
        "1600",
        "http://mewa-styl.ru/imgtmp/orign/data/1/gab92.jpg",
        "42"
    ],
    "http://mewa-styl.ru/ishop/product/485": [
        "485",
        "10.Купальник Chica разм.36-44 (42-50) ",
        "Купальник Chica разм.36-44 (42-50) . С чашкой , на косточках , съемные вставки Push-up . Бретельки регулируются и отсоединяются . Надежная металлическая застежка с возможностью регулировки объема .  ",
        "1100",
        "http://mewa-styl.ru/imgtmp/orign/data/1/gab83.jpg",
        "46"
    ],
    "http://mewa-styl.ru/ishop/product/486": [
        "486",
        "11.Купальник Chica разм.36-44 (42-50) ",
        "Купальник Chica разм.36-44 (42-50) . С чашкой , на косточках , съемные вставки Push-up . Бретельки регулируются и отсоединяются . Надежная металлическая застежка с возможностью регулировки объема .  ",
        "1100",
        "http://mewa-styl.ru/imgtmp/orign/data/1/gab86.jpg",
        "42, 46"
    ],
    "http://mewa-styl.ru/ishop/product/491": [
        "491",
        "15.Купальник Chica разм.36-44 (42-50)",
        "Купальник Chica разм.36-44 (42-50) . С чашкой , на косточках , съемные вставки Push-up . Бретельки регулируются и отсоединяются . Надежная металлическая застежка с возможностью регулировки объема .  ",
        "1600",
        "http://mewa-styl.ru/imgtmp/orign/data/1/gab87.jpg",
        "44, 46"
    ],
    "http://mewa-styl.ru/ishop/product/551": [
        "551",
        "16.Купальник Chica разм.36-44 (42-50)  ",
        "Купальник Chica разм.36-44 (42-50) . С чашкой , на косточках , съемные вставки Push-up . Бретельки регулируются и отсоединяются . Надежная металлическая застежка с возможностью регулировки объема .",
        "1100",
        "http://mewa-styl.ru/imgtmp/orign/data/1/gab192.jpg",
        "46"
    ],
    "http://mewa-styl.ru/ishop/product/662": [
        "662",
        "41 . Купальник ashley разм.36-44 (42-50 ) ",
        "Купальник Gabbiano Аshley разм. 36-44 (42-50). С чашкой , на косточках , съемные вставки Push-up . Бретелько отстегиваются и регулируются . На спине надежная металлическая застежка .",
        "1600",
        "http://mewa-styl.ru/imgtmp/orign/data/2018/gab663.jpg",
        "42B, 44D"
    ],
    "http://mewa-styl.ru/ishop/product/724": [
        "",
        "",
        "",
        "",
        "",
        ""
    ],
    "http://mewa-styl.ru/ishop/product/734": [
        "734",
        "43а.Купальник ashley разм.36-44 (42-50 )  ",
        "Купальник ashley разм.36-44 (42-50 ) . С чашкой , на косточках , съемные вставки Push-up . Бретельки регулируются и отстегиваются . Сзади надежная металлическая застежка с возможностью регулировки объема .",
        "1600",
        "http://mewa-styl.ru/imgtmp/orign/data/2/gab593.jpg",
        "42B, 44D"
    ],
    "http://mewa-styl.ru/ishop/product/741": [
        "741",
        "43б.Купальник ashley разм.36-44 (42-50 ) ",
        "Купальник ashley разм.36-44 (42-50 ) . С чашкой , на косточках , съемные вставки Push-up . Бретельки регулируются и отстегиваются . Сзади надежная металлическая застежка с возможностью регулировки объема .",
        "1600",
        "http://mewa-styl.ru/imgtmp/orign/data/2018/gab583.jpg",
        "42B, 44D"
    ],
    "http://mewa-styl.ru/ishop/product/765": [
        "765",
        "43в.Купальник ashley разм.36-44 (42-50 )  ",
        "Купальник ashley разм.36-44 (42-50 ) . С чашкой , на косточках , съемные вставки Push-up . Бретельки регулируются и отстегиваются . Сзади надежная металлическая застежка с возможностью регулировки объема .",
        "1600",
        "http://mewa-styl.ru/imgtmp/orign/data/2018/gab615.jpg",
        "42B, 44D"
    ],
    "http://mewa-styl.ru/ishop/product/783": [
        "783",
        "44в.Купальник ashley разм.36-44 (42-50 ) ",
        "Купальник Gabbiano Аshley разм. 36-44 (42-50). С чашкой , на косточках , съемные вставки Push-up . Бретельки регулируются о отстегиваются . Сзади надежная металлическая застежка с возможностью регулировки объема .",
        "1600",
        "http://mewa-styl.ru/imgtmp/orign/data/2018/gab648.jpg",
        "42B, 44B, 44D, 46D"
    ],
    "http://mewa-styl.ru/ishop/product/784": [
        "784",
        "45а.Купальник ashley разм.36-44 (42-50 ) ",
        "Купальник Gabbiano Аshley разм. 36-44 (42-50). С чашкой , на косточках , съемные вставки Push-up . Бретельки регулируются о отстегиваются . Сзади надежная металлическая застежка с возможностью регулировки объема .",
        "1600",
        "http://mewa-styl.ru/imgtmp/orign/data/2018/gab649.jpg",
        "44D"
    ],
    "http://mewa-styl.ru/ishop/product/796": [
        "796",
        "45г.Купальник ashley разм.36-44 (42-50 )  ",
        "Купальник ashley разм.36-44 (42-50 ) . С чашкой , на косточках , съемные вставки Push-up . Бретельки регулируются и отстегиваются . Сзади надежная металлическая застежка с возможностью регулировки объема .",
        "1600",
        "http://mewa-styl.ru/imgtmp/orign/data/2018/gab676.jpg",
        "42B"
    ],
    "http://mewa-styl.ru/Jenny": [
        "http://mewa-styl.ru/Jenny",
        "51 . Купальник Jenny разм.36",
        "Купальник Jenny разм.36 . С чашкой , на косточках , съемные вставки Push-up . Бретельки регулируются и отсоединяются . Надежная металлическая застежка с возможностью регулировки объема .   ",
        "1600",
        "http://mewa-styl.ru/imgtmp/orign/data/2919/gab297.jpg",
        "42B"
    ],
    "http://mewa-styl.ru/ishop/product/933": [
        "933",
        "52.Купальник Anabel",
        "Купальник Anabel . Лиф в виде треугольных чашек , завязки на шее и объеме . С чашкой , без косточек , push-ap . Благодаря эффекту обжимания, он мягко формирует и подчеркивает бюст.",
        "2500",
        "http://mewa-styl.ru/imgtmp/orign/data/1/Gabbiano2022/gab0001.jpg",
        "42B, 44B, 44C, 44D, 44E, 46B, 46C, 46D, 48B, 48C, 50B, 50C"
    ],
    "http://mewa-styl.ru/ishop/product/658": [
        "658",
        "53 . Купальник Anabel ",
        "Купальник Anabel  . Push - up .  С чашкой , без косточек . На шее и на спине завязки .",
        "1300",
        "http://mewa-styl.ru/imgtmp/orign/data/2/gab470.jpg",
        "42B, 42C, 42C"
    ],
    "http://mewa-styl.ru/ishop/product/813": [
        "813",
        "56в . Купальник Anabel  разм.36-44 (42-50 ) ",
        "Купальник Anabel  разм.36-44 (42-50 ) .  С чашкой , без косточек .  Push-up . На шее и на спине завязки . ",
        "1800",
        "http://mewa-styl.ru/imgtmp/orign/data/2919/gab738.jpg",
        "42E, 42F, 44D, 44F"
    ],
    "http://mewa-styl.ru/ishop/product/826": [
        "826",
        "56г.Купальник Anabel G01  разм.36-44 (42-50 ) ",
        "Купальник Anabel  разм.36-44 (42-50 ) .  С чашкой , без косточек .  Push-up . На шее и на спине завязки . ",
        "2100",
        "http://mewa-styl.ru/imgtmp/orign/data/2919/gab713.jpg",
        "42B, 42C, 44B, 44D, 44E, 44F, 46D, 46E"
    ],
    "http://mewa-styl.ru/ishop/product/845": [
        "845",
        "56ж.Купальник Anabel  разм.36-44 (42-50 ) ",
        "Купальник Anabel  разм.36-44 (42-50 ) .  С чашкой , без косточек .  Push-up . На шее и на спине завязки .  ",
        "2100",
        "http://mewa-styl.ru/imgtmp/orign/data/2919/gab731.jpg",
        "42E"
    ],
    "http://mewa-styl.ru/ishop/product/847": [
        "847",
        "56з.Купальник Anabel  разм.36-44 (42-50 ) ",
        "Купальник Anabel  разм.36-44 (42-50 ) .  С чашкой , без косточек .  Push-up . На шее и на спине завязки . ",
        "2000",
        "http://mewa-styl.ru/imgtmp/orign/data/2919/gab737.jpg",
        "42C, 42D, 42E, 42F, 44E, 44F"
    ],
    "http://mewa-styl.ru/ishop/product/851": [
        "851",
        "56и.Купальник Anabel  разм.36-44 (42-50 ) ",
        "Купальник Anabel . Лиф в виде треугольных чашек- завязки на шее и объеме.Чашка без косточки с push-ap , благодаря эффекту обжимания, он мягко формирует и подчеркивает бюст.",
        "2500",
        "http://mewa-styl.ru/imgtmp/orign/data/2919/gab742.jpg",
        "42B, 44B, 46B"
    ],
    "http://mewa-styl.ru/ishop/product/857": [
        "857",
        "56л. Купальник Anabel  разм.36-44 (42-50 )   ",
        "Купальник Anabel . Лиф в виде треугольных чашек , завязки на шее и объеме . С чашкой , без косточек , push-ap . Благодаря эффекту обжимания, он мягко формирует и подчеркивает бюст.",
        "2100",
        "http://mewa-styl.ru/imgtmp/orign/data/2919/gab749.jpg",
        "42B, 42D, 42E, 44B, 44D, 44E, 44F, 46B, 46C, 46D, 46E"
    ],
    "http://mewa-styl.ru/ishop/product/931": [
        "931",
        "57а.Купальник Anabel",
        "Купальник Anabel . Лиф в виде треугольных чашек , завязки на шее и объеме . С чашкой , без косточек , push-ap . Благодаря эффекту обжимания, он мягко формирует и подчеркивает бюст.",
        "2300",
        "http://mewa-styl.ru/imgtmp/orign/data/2/data3011gab00006.jpg",
        "42B, 42D, 44B, 44C, 46B"
    ],
    "http://mewa-styl.ru/ishop/product/932": [
        "932",
        "57б.Купальник Anabel",
        "Купальник Anabel . Лиф в виде треугольных чашек , завязки на шее и объеме . С чашкой , без косточек , push-ap . Благодаря эффекту обжимания, он мягко формирует и подчеркивает бюст.",
        "2500",
        "http://mewa-styl.ru/imgtmp/orign/data/2/data3011gab00007.jpg",
        "42B, 44B, 44C, 46B"
    ],
    "http://mewa-styl.ru/ishop/product/623": [
        "623",
        "59 . Купальник Esther разм.40-46 (46-52)",
        "Купальник Esther разм.40-46 (46-52). С чашкой , на косточках . Плечевые лямки регулируются . Сэади надежная металлическая застежка  .  Роскошная модель на большую грудь . ",
        "2100",
        "http://mewa-styl.ru/imgtmp/orign/data/2919/gab-7.jpg",
        "44I"
    ],
    "http://mewa-styl.ru/ishop/product/752": [
        "752",
        "65.Купальник Esther разм.40-46 (46-52) ",
        "Купальник Esther разм.40-46 (46-52). С чашкой , на косточках . Плечевые лямки регулируются . Сэади надежная металлическая застежка  .  Роскошная модель на большую грудь . ",
        "2100",
        "http://mewa-styl.ru/imgtmp/orign/data/2919/gab734.jpg",
        "44G, 44H"
    ],
    "http://mewa-styl.ru/ishop/product/754": [
        "754",
        "66.Купальник Esther  разм.40-46 (46-52) ",
        "Купальник Esther  . С чашкой , на косточках . Плечевые лямки регулируются . Сэади надежная металлическая застежка  .  Роскошная модель на большую грудь . ",
        "2500",
        "http://mewa-styl.ru/imgtmp/orign/data/2919/data2919gab0002.jpg",
        "46C, 46D, 46F, 48C, 48D, 48E, 48F, 50C, 50D, 50E, 50F, 52C, 52D, 52Eг"
    ],
    "http://mewa-styl.ru/ishop/product/808": [
        "808",
        "67б. Купальник Esther разм.36-44 (42-50) ",
        "Купальник Esther разм.42-46 (48-52) . С чашкой , на косточках . Плечевые лямки регулируются . Сэади надежная металлическая застежка  .  Роскошная модель на большую грудь . ",
        "2500",
        "http://mewa-styl.ru/imgtmp/orign/data/gab0001.jpg.jpg",
        "48D, 50D, 50E, 50F, 52C"
    ],
    "http://mewa-styl.ru/ishop/product/865": [
        "865",
        "67к . Купальник Esther ",
        "Купальник Esther разм.36-44 (42-50) . С чашкой , на косточках . Плечевые лямки регулируются . Сэади надежная металлическая застежка  .  Роскошная модель на большую грудь . ",
        "2100",
        "http://mewa-styl.ru/imgtmp/orign/data/2919/gab762.jpg",
        "44F, 44G, 44H"
    ],
    "http://mewa-styl.ru/ishop/product/876": [
        "876",
        "68б. Купальник Esther ",
        "Купальник Esther разм.36-44 (42-50) . С чашкой , на косточках . Плечевые лямки регулируются . Сэади надежная металлическая застежка  .  Роскошная модель на большую грудь . ",
        "2500",
        "http://mewa-styl.ru/imgtmp/orign/data/gab765.jpg",
        "48D"
    ],
    "http://mewa-styl.ru/ishop/product/880": [
        "880",
        "68г.. Купальник Esther ",
        "Купальник Esther  . С чашкой , на косточках . Плечевые лямки регулируются . Сэади надежная металлическая застежка  .  Роскошная модель на большую грудь .",
        "2500",
        "http://mewa-styl.ru/imgtmp/orign/data/1/FN7A5275.jpg.jpg",
        "46C, 46D, 46F, 48C, 48D, 48E, 48F, 50C, 50D, 50E, 50F, 52C, 52D, 52E"
    ],
    "http://mewa-styl.ru/ishop/product/885": [
        "885",
        "68д.Купальник Esther разм.36-44 (42-50)",
        "Купальник Esther  . С чашкой , на косточках . Плечевые лямки регулируются . Сэади надежная металлическая застежка  .  Роскошная модель на большую грудь ",
        "2100",
        "http://mewa-styl.ru/imgtmp/orign/data/2919/gab760.jpg",
        "50E"
    ],
    "http://mewa-styl.ru/ishop/product/898": [
        "898",
        "68е. Купальник Esther ",
        "Купальник Esther  . С чашкой , на косточках . Плечевые лямки регулируются . Сэади надежная металлическая застежка  .  Роскошная модель на большую грудь .",
        "2500",
        "http://mewa-styl.ru/imgtmp/orign/data/1/FN7A2825-r.jpg.jpg",
        "46C, 46D, 46F, 48C, 48D, 48E, 48F, 50C, 50D, 50E, 50F, 52C, 52D, 52E"
    ],
    "http://mewa-styl.ru/ishop/product/899": [
        "899",
        "68ж. Купальник Esther ",
        "Купальник Esther  . С чашкой , на косточках . Плечевые лямки регулируются . Сэади надежная металлическая застежка  .  Роскошная модель на большую грудь .",
        "2500",
        "http://mewa-styl.ru/imgtmp/orign/data/2919/gab288.jpg",
        "48D, 48F, 48G, 52C"
    ],
    "http://mewa-styl.ru/ishop/product/944": [
        "944",
        ".Купальник Esther  разм.40-46 (46-52) ",
        "Купальник Esther  . С чашкой , на косточках . Плечевые лямки регулируются . Сэади надежная металлическая застежка  .  Роскошная модель на большую грудь .",
        "2100",
        "http://mewa-styl.ru/imgtmp/orign/data/1/image.png",
        "50D"
    ],
    "http://mewa-styl.ru/ishop/product/502": [
        "502",
        "156.Купальник Gaby разм. 36-42 (42-48) ",
        "Купальник Gaby разм. 36-42 (42-48). С чашкой , без косточкек . На шее и на спине завязки .",
        "1300",
        "http://mewa-styl.ru/imgtmp/orign/data/1/gab91.jpg",
        "42, 44"
    ],
    "http://mewa-styl.ru/ishop/product/625": [
        "625",
        "184 . Купальник Marita  разм.36",
        "Купальник Marita  разм.36 . С чашкой , на косточках , съемные вставки Push-up . Бретельки регулируются и отсоединяются . Надежная металлическая застежка с возможностью регулировки объема .   ",
        "1800",
        "http://mewa-styl.ru/imgtmp/orign/data/Gabbiano/gab369.jpg",
        "42"
    ],
    "http://mewa-styl.ru/ishop/product/733": [
        "733",
        "277.Купальник Ana разм.36-44 (42-50 ) ",
        "Купальник Ana   разм.36-44 (42-50 ) .  С чашкой , без косточек .  Push-up . На шее и на спине завязки .",
        "1600",
        "http://mewa-styl.ru/imgtmp/orign/data/2018/gab572.jpg",
        "44D"
    ],
    "http://mewa-styl.ru/ishop/product/735": [
        "735",
        "279..Купальник Rita разм.36-44 (42-50 )  ",
        "Купальник Rita разм.36-44 (42-50 ). С чашкой , на косточках , съемные вставки Push-up . Бретельки регулируются. Сзади надежная металлическая застежка с возможностью регулировки объема .",
        "1600",
        "http://mewa-styl.ru/imgtmp/orign/data/2018/gab574.jpg",
        "44D"
    ],
    "http://mewa-styl.ru/ishop/product/736": [
        "736",
        "280.Купальник Rita разм.36-44 (42-50 )",
        "Купальник Rita разм.36-44 (42-50 ). С чашкой , на косточках , съемные вставки Push-up . Бретельки регулируются. Сзади надежная металлическая застежка с возможностью регулировки объема .",
        "1600",
        "http://mewa-styl.ru/imgtmp/orign/data/2919/gab307.jpg",
        "42B, 44C, 44D"
    ],
    "http://mewa-styl.ru/ishop/product/747": [
        "747",
        "291.Купальник Rita разм.36-44 (42-50 ) ",
        "Купальник Rita разм.36-44 (42-50 ). С чашкой , на косточках , съемные вставки Push-up . Бретельки регулируются. Сзади надежная металлическая застежка с возможностью регулировки объема .",
        "1600",
        "http://mewa-styl.ru/imgtmp/orign/data/2018/gab589.jpg",
        "44D"
    ],
    "http://mewa-styl.ru/ishop/product/770": [
        "770",
        "312.Купальник Rita разм.36-44 (42-50 ) ",
        "Купальник Rita разм.36-44 (42-50 ). С чашкой , на косточках , съемные вставки Push-up . Бретельки регулируются. Сзади надежная металлическая застежка с возможностью регулировки объема .",
        "1800",
        "http://mewa-styl.ru/imgtmp/orign/data/2919/gab773.jpg",
        "42B, 44B, 44C, 44D, 46B, 46C, 46D, 48B"
    ],
    "http://mewa-styl.ru/ishop/product/771": [
        "771",
        "313.Купальник Rita разм.36-44 (42-50 ) ",
        "Купальник Rita разм.36-44 (42-50 ). С чашкой , на косточках , съемные вставки Push-up . Бретельки регулируются. Сзади надежная металлическая застежка с возможностью регулировки объема .",
        "1600",
        "http://mewa-styl.ru/imgtmp/orign/data/2018/gab622.jpg",
        "44D"
    ],
    "http://mewa-styl.ru/ishop/product/772": [
        "772",
        "314.Купальник Rita разм.36-44 (42-50 ) ",
        "Купальник Rita разм.36-44 (42-50 ). С чашкой , на косточках , съемные вставки Push-up . Бретельки регулируются. Сзади надежная металлическая застежка с возможностью регулировки объема .",
        "1600",
        "http://mewa-styl.ru/imgtmp/orign/data/2018/gab624.jpg",
        "42B, 44C, 44D, 46B, 46C, 46D"
    ],
    "http://mewa-styl.ru/ishop/product/773": [
        "773",
        "315.Купальник Rita разм.36-44 (42-50 ) ",
        "Купальник Rita разм.36-44 (42-50 ). С чашкой , на косточках , съемные вставки Push-up . Бретельки регулируются. Сзади надежная металлическая застежка с возможностью регулировки объема .",
        "1600",
        "http://mewa-styl.ru/imgtmp/orign/data/2919/gab771.jpg",
        "42B, 44B, 44C, 44D, 46B, 46C, 46D, 48B, 48C"
    ],
    "http://mewa-styl.ru/ishop/product/775": [
        "775",
        "317.Купальник Rita разм.36-44 (42-50 ) ",
        "Купальник Rita разм.36-44 (42-50 ). С чашкой , на косточках , съемные вставки Push-up . Бретельки регулируются. Сзади надежная металлическая застежка с возможностью регулировки объема .",
        "1600",
        "http://mewa-styl.ru/imgtmp/orign/data/2018/gab626.jpg",
        "42B, 44B, 44C, 44D, 46C, 46D"
    ],
    "http://mewa-styl.ru/ishop/product/776": [
        "776",
        "318.Купальник Rita разм.36-44 (42-50 ) ",
        "Купальник Rita разм.36-44 (42-50 ). С чашкой , на косточках , съемные вставки Push-up . Бретельки регулируются. Сзади надежная металлическая застежка с возможностью регулировки объема .",
        "1600",
        "http://mewa-styl.ru/imgtmp/orign/data/2018/gab635.jpg",
        "42B, 44B, 44C, 44D, 46B, 46D"
    ],
    "http://mewa-styl.ru/ishop/product/787": [
        "787",
        "329.Купальник Ana   разм.36-44 (42-50 ) ",
        "Купальник Ana   разм.36-44 (42-50 ) .  С чашкой , без косточек .  Push-up . На шее и на спине завязки .",
        "1600",
        "http://mewa-styl.ru/imgtmp/orign/data/2018/gab656.jpg",
        "44D, 46D"
    ],
    "http://mewa-styl.ru/ishop/product/794": [
        "794",
        "331.Купальник Rita разм.36-44 (42-50 ) ",
        "Купальник Rita разм.36-44 (42-50 ). С чашкой , на косточках , съемные вставки Push-up . Бретельки регулируются. Сзади надежная металлическая застежка с возможностью регулировки объема .",
        "1600",
        "http://mewa-styl.ru/imgtmp/orign/data/2919/gab770.jpg",
        "42B, 44B, 44C, 44D, 46B, 46C, 46D, 48B"
    ],
    "http://mewa-styl.ru/ishop/product/849": [
        "849",
        "332.Купальник Rita разм.36-44 (42-50 ) ",
        "Купальник Rita разм.36-44 (42-50 ). С чашкой , на косточках , съемные вставки Push-up . Бретельки регулируются. Сзади надежная металлическая застежка с возможностью регулировки объема .",
        "1600",
        "http://mewa-styl.ru/imgtmp/orign/data/2919/gab769.jpg",
        "42B, 44B, 44C, 44D, 46B, 46C, 46D, 48B"
    ],
    "http://mewa-styl.ru/ishop/product/143": [
        "143",
        "900. Купальник diana разм.38",
        "Купальник Gabbiano diana разм.38 . С чашкой , без косточек , съемные вставки Push-up . Бретельки регулируются. ",
        "1800",
        "http://mewa-styl.ru/imgtmp/orign/data/SlideShow/str159_Gabbiano_1428_sty14_A4.jpg",
        "44"
    ],
    "http://mewa-styl.ru/ishop/product/616": [
        "616",
        "900 . Купальник Zaira",
        " Купальник Zaira .  С чашкой , на косточках , съемные вставки Push-up . Бретельки регулируются и отсоединяются . Надежная металлическая застежка с возможностью регулировки объема .",
        "2500",
        "http://mewa-styl.ru/imgtmp/orign/data/Gabbiano/gab236.jpg",
        "44, 46"
    ],
    "http://mewa-styl.ru/ishop/product/650": [
        "650",
        "901 . Купальник Lara ",
        "Купальник Lara . С чашкой , без косточек . На шее и на спине завязки . ",
        "2500",
        "http://mewa-styl.ru/imgtmp/orign/data/2919/gab295.jpg",
        "42, 42C, 42D, 44, 44D, 46, 46C, 48"
    ],
    "http://mewa-styl.ru/ishop/product/758": [
        "758",
        "901.Купальник Elmira разм. 38 - 46  ",
        "Купальник Elmira разм. 38 - 46 . С чашкой , на косточках . Плечевые лямки регулируются , на спине застежка .",
        "2300",
        "http://mewa-styl.ru/imgtmp/orign/data/2018/gab603.jpg",
        "44"
    ],
    "http://mewa-styl.ru/ishop/product/759": [
        "759",
        "901. Купальник Beatriz разм. 38 - 44",
        "Купальник Beatriz разм. 38 - 44 . С чашкой , на косточках . Плечевые лямки регулируются , на спине застежка .",
        "2300",
        "http://mewa-styl.ru/imgtmp/orign/data/2018/gab606.jpg",
        "44"
    ],
    "http://mewa-styl.ru/ishop/product/638": [
        "638",
        "949 . купальник tankini разм.36-42 (42-48) ",
        "Купальник Gabbiano tankini разм.36-42 (42-48). С чашкой , на косточках . съемные вставки Push-up . Бретельки регулируются и отсоединяются . На спине завязки .",
        "2300",
        "http://mewa-styl.ru/imgtmp/orign/data/Gabbiano/gab289.jpg",
        "44"
    ],
    "http://mewa-styl.ru/ishop/product/641": [
        "641",
        "951 . купальник tankini разм.38",
        "Купальник Gabbiano tankini разм.36-42 (42-48). С чашкой , на косточках . съемные вставки Push-up . Бретельки регулируются и отсоединяются . На спине завязки .",
        "2300",
        "http://mewa-styl.ru/imgtmp/orign/data/Gabbiano/gab332.jpg",
        "44"
    ],
    "http://mewa-styl.ru/ishop/product/683": [
        "683",
        "953 . купальник tankini разм.36-42 (42-48) ",
        "Купальник Gabbiano tankini разм.36-42 (42-48). С чашкой , на косточках . съемные вставки Push-up . Бретельки регулируются и отсоединяются . На спине завязки .",
        "2300",
        "http://mewa-styl.ru/imgtmp/orign/data/2/gab428.jpg",
        "44, 46"
    ],
    "http://mewa-styl.ru/ishop/product/718": [
        "718",
        "955 . купальник tankini ",
        "Купальник Gabbiano tankini разм.38 - 46 (44-52). С чашкой , на косточках . съемные вставки Push-up . Бретельки регулируются  . На спине завязки . ",
        "2500",
        "http://mewa-styl.ru/imgtmp/orign/data/Gabbiano/gab237.jpg",
        "46"
    ],
    "http://mewa-styl.ru/ishop/product/719": [
        "719",
        "956 . купальник tankini ",
        "Купальник Gabbiano tankini разм.38 - 46 (44-52). С чашкой , на косточках . съемные вставки Push-up . Бретельки регулируются  . На спине завязки . ",
        "2500",
        "http://mewa-styl.ru/imgtmp/orign/data/Gabbiano/gab238.jpg",
        "44, 46"
    ],
    "http://mewa-styl.ru/ishop/product/720": [
        "720",
        "957. купальник tankini ",
        "Купальник Gabbiano tankini разм.38 - 46 (44-52). С чашкой , на косточках . съемные вставки Push-up . Бретельки регулируются  . На спине завязки . ",
        "2500",
        "http://mewa-styl.ru/imgtmp/orign/data/2919/gab701.jpg",
        "44"
    ],
    "http://mewa-styl.ru/ishop/product/846": [
        "846",
        "958.купальник tankini ",
        "Купальник Gabbiano tankini разм.36-42 (42-48). С чашкой , на косточках . съемные вставки Push-up . Бретельки регулируются и отсоединяются . На спине завязки .",
        "2500",
        "http://mewa-styl.ru/imgtmp/orign/data/2919/gab730.jpg",
        "46"
    ],
    "http://mewa-styl.ru/ishop/product/873": [
        "873",
        "961.Купальник  Leticia разм. 36-44",
        "Купальник Leticia разм. 36-44 . С чашкой , на косточках . Плечевые лямки регулируются , на спине застежка .",
        "2300",
        "http://mewa-styl.ru/imgtmp/orign/data/gab764.jpg",
        "44, 46"
    ],
    "http://mewa-styl.ru/ishop/product/904": [
        "904",
        "962. Купальник Karen ",
        "Купальник Karen . С чашкой , на косточках . Плечевые лямки отстегиваются и регулируются , на спине застежка .",
        "2500",
        "http://mewa-styl.ru/imgtmp/orign/data/2919/gab293.jpg",
        "44, 46, 46C, 48, 50, 52"
    ],
    "http://mewa-styl.ru/ishop/product/934": [
        "934",
        "963.Купальник Karen",
        "Купальник Karen . С чашкой , на косточках . Плечевые лямки отстегиваются и регулируются , на спине застежка .",
        "2500",
        "http://mewa-styl.ru/imgtmp/orign/data/2/data3011gab000010.jpg",
        "44C, 46, 48, 50, 52"
    ],
    "http://mewa-styl.ru/ishop/product/914": [
        "914",
        "964. Купальник Lara  ",
        "Купальник Lara . С чашкой , без косточек . На шее и на спине завязки . ",
        "2500",
        "http://mewa-styl.ru/imgtmp/orign/data/2919/gab321.jpg",
        "42C"
    ],
    "http://mewa-styl.ru/ishop/product/919": [
        "919",
        "965. Купальник Lara  ",
        "Купальник Lara . С чашкой , без косточек . На шее и на спине завязки . ",
        "2500",
        "http://mewa-styl.ru/imgtmp/orign/data/2919/gab327.jpg",
        "46"
    ],
    "http://mewa-styl.ru/ishop/product/120": [
        "120",
        "Купальник manuela разм. 36",
        "Купальник Elin разм.36 . С чашкой , на косточках , съемные вставки Push-up . Бретельки регулируются и отсоединяются . Надежная металлическая застежка с возможностью регулировки объема .  ",
        "1100",
        "http://mewa-styl.ru/imgtmp/orign/data/Gabbiano/3.jpg",
        "42"
    ],
    "http://mewa-styl.ru/ishop/product/121": [
        "121",
        "Купальник darla разм. 36",
        "Купальник Gabbiano Darla разм. 36 . С чашкой , на косточках , съемные вставки Push-up . Бретельки регулируются  . Надежная металлическая застежка с возможностью регулировки объема . ",
        "1100",
        "http://mewa-styl.ru/imgtmp/orign/data/Gabbiano/49.jpg",
        "42"
    ],
    "http://mewa-styl.ru/ishop/product/166": [
        "166",
        "Купальник Gabbiano Elin разм. 36",
        "Купальник Gabbiano Elin разм. 36 . С чашкой , на косточках , съемные вставки Push-up . Бретельки регулируются и отсоединяются . Надежная металлическая застежка .",
        "1100",
        "http://mewa-styl.ru/imgtmp/orign/data/1/gab137.jpg",
        "42"
    ],
    "http://mewa-styl.ru/ishop/product/185": [
        "185",
        "Купальник Elin разм.36",
        "Купальник Elin разм.36 . С чашкой , на косточках , съемные вставки Push-up . Бретельки регулируются и отсоединяются . Надежная металлическая застежка с возможностью регулировки объема .  ",
        "1100",
        "http://mewa-styl.ru/imgtmp/orign/data/Gabbiano/gab250.jpg",
        "42"
    ],
    "http://mewa-styl.ru/ishop/product/271": [
        "271",
        "Купальник aisha   разм. 36",
        "Купальник Gabbiano aisha разм. 36 . С чашкой , на косточках , съемные вставки Push-up . Бретельки регулируются и отсоединяются . Надежная металлическая застежка с возможностью регулировки .",
        "950",
        "http://mewa-styl.ru/imgtmp/orign/data/Gabbiano/gab406.jpg",
        "42"
    ],
    "http://mewa-styl.ru/ishop/product/294": [
        "294",
        "Купальник Selena  разм.36 ",
        "Купальник Gabbiano  Selena разм. 36 . С чашкой , на косточках , съемные вставки Push-up . Бретельки регулируются и отсоединяются . Надежная металлическая застежка . ",
        "950",
        "http://mewa-styl.ru/imgtmp/orign/data/1/gab147.jpg",
        "42"
    ],
    "http://mewa-styl.ru/ishop/product/510": [
        "510",
        "Купальник Esme разм.36",
        "Купальник Esme разм.36 . С чашкой , на косточках , съемные вставки Push-up . Бретельки регулируются и отсоединяются . Надежная металлическая застежка с возможностью регулировки объема .   ",
        "1100",
        "http://mewa-styl.ru/imgtmp/orign/data/2018/gab689.jpg",
        "42"
    ],
    "http://mewa-styl.ru/ishop/product/656": [
        "656",
        "Купальник Esme разм.36 ",
        "Купальник Esme разм.36 . С чашкой , на косточках , съемные вставки Push-up . Бретельки регулируются и отсоединяются . Надежная металлическая застежка с возможностью регулировки объема .   ",
        "1100",
        "http://mewa-styl.ru/imgtmp/orign/data/Gabbiano/gab356.jpg",
        "42"
    ],
    "http://mewa-styl.ru/ishop/product/192": [
        "192",
        "Купальник  Aisha разм. 36",
        "Купальник Gabbiano  Aisha разм. 36 . С чашкой , на косточках , съемные вставки Push-up . Бретельки регулируются и отсоединяются . Надежная металлическая застежка с возможностью регулировки объема .",
        "950",
        "http://mewa-styl.ru/imgtmp/orign/data/start/str120g_Gabbiano_8107_sty13_mnt.jpg",
        "42"
    ],
    "http://mewa-styl.ru/ishop/product/519": [
        "",
        "",
        "",
        "",
        "",
        ""
    ],
    "http://mewa-styl.ru/ishop/product/707": [
        "",
        "",
        "",
        "",
        "",
        ""
    ],
    "http://mewa-styl.ru/ishop/product/732": [
        "",
        "",
        "",
        "",
        "",
        ""
    ],
    "http://mewa-styl.ru/ishop/product/882": [
        "",
        "",
        "",
        "",
        "",
        ""
    ],
    "http://mewa-styl.ru/ishop/product/745": [
        "",
        "",
        "",
        "",
        "",
        ""
    ]
}